{
    "lbb": "Error extracting job infos for lbb: 'NoneType' object has no attribute 'find'",
    "stb": "Error extracting job infos for stb: 'NoneType' object has no attribute 'text'",
    "icom": "Error extracting job infos for icom: 'NoneType' object has no attribute 'text'",
    "inab": "Error extracting job infos for inab: 'NoneType' object has no attribute 'text'",
    "e3d": "Error extracting job infos for e3d: 'NoneType' object has no attribute 'text'",
    "iww": "Error extracting job infos for iww: 'NoneType' object has no attribute 'text'",
    "ifam": "Error extracting job infos for ifam: 'NoneType' object has no attribute 'text'",
    "gia": "Error extracting job infos for gia: 'NoneType' object has no attribute 'text'",
    "Schuessler-Preis": "Error extracting job infos for Schuessler-Preis: 'NoneType' object has no attribute 'find'",
    "Holzbaupreis": "Error extracting job infos for Holzbaupreis: 'NoneType' object has no attribute 'find'",
    "rwth": "Error fetching content for https://www.rwth-aachen.de/cms/root/Die-RWTH/Arbeiten-an-der-RWTH/~buym/RWTH-Jobportal/?search=&showall=1&aaaaaaaaaaaaanr=&frist=&aaaaaaaaaaaaanq=&aaaaaaaaaaaaany=Einstellung+als+Studentische+Hilfskraft&aaaaaaaaaaaaans=&aaaaaaaaaaaaanw=&aaaaaaaaaaaaanv=&aaaaaaaaaaaaanx=: Message: timeout: Timed out receiving message from renderer: -0.004\n  (Session info: chrome=143.0.7499.169)\nStacktrace:\n#0 0x555a8927740a <unknown>\n#1 0x555a88cab76b <unknown>\n#2 0x555a88c9380a <unknown>\n#3 0x555a88c934ed <unknown>\n#4 0x555a88c913a7 <unknown>\n#5 0x555a88c91cbf <unknown>\n#6 0x555a88ca0480 <unknown>\n#7 0x555a88cb9b47 <unknown>\n#8 0x555a88cc01fb <unknown>\n#9 0x555a88c923e8 <unknown>\n#10 0x555a88cb98f8 <unknown>\n#11 0x555a88d48639 <unknown>\n#12 0x555a88cef7b2 <unknown>\n#13 0x555a88cf0461 <unknown>\n#14 0x555a8923fdf9 <unknown>\n#15 0x555a89242d5d <unknown>\n#16 0x555a89228b41 <unknown>\n#17 0x555a8924393b <unknown>\n#18 0x555a8920f870 <unknown>\n#19 0x555a89264828 <unknown>\n#20 0x555a892649fc <unknown>\n#21 0x555a89276763 <unknown>\n#22 0x7f5d31e9caa4 <unknown>\n#23 0x7f5d31f29c6c <unknown>\n"
}